personal_mnemonic_medium/__init__.py
personal_mnemonic_medium/card_pipeline.py
personal_mnemonic_medium/cli.py
personal_mnemonic_medium/docs_example.py
personal_mnemonic_medium/main.py
personal_mnemonic_medium/exporters/__init__.py
personal_mnemonic_medium/exporters/base.py
personal_mnemonic_medium/exporters/anki/__init__.py
personal_mnemonic_medium/exporters/anki/anki_css.py
personal_mnemonic_medium/exporters/anki/globals.py
personal_mnemonic_medium/exporters/anki/package_generator.py
personal_mnemonic_medium/exporters/anki/sync.py
personal_mnemonic_medium/exporters/anki/card_types/base.py
personal_mnemonic_medium/exporters/anki/card_types/cloze.py
personal_mnemonic_medium/exporters/anki/card_types/qa.py
personal_mnemonic_medium/exporters/markdown_to_html/html_compiler.py
personal_mnemonic_medium/exporters/url_generators/1writer_url.py
personal_mnemonic_medium/exporters/url_generators/obsidian_url.py
personal_mnemonic_medium/note_factories/__init__.py
personal_mnemonic_medium/note_factories/base.py
personal_mnemonic_medium/note_factories/markdown.py
personal_mnemonic_medium/note_factories/note.py
personal_mnemonic_medium/prompt_extractors/base.py
personal_mnemonic_medium/prompt_extractors/cloze_extractor.py
personal_mnemonic_medium/prompt_extractors/prompt.py
personal_mnemonic_medium/prompt_extractors/qa_extractor.py
personal_mnemonic_medium/tests/__init.py
personal_mnemonic_medium/tests/integration_test.sh
personal_mnemonic_medium/tests/test.md
personal_mnemonic_medium/tests/exporters/anki/test_card_converter.py
personal_mnemonic_medium/tests/exporters/anki/test_package_generator.py
personal_mnemonic_medium/tests/note_factories/test_markdown_extractor.py
personal_mnemonic_medium/tests/prompt_extractors/test_cloze_extractor.py
personal_mnemonic_medium/tests/prompt_extractors/test_qa_prompt_extractor.py
personal_mnemonic_medium/tests/test_md_files/Bensår.md
personal_mnemonic_medium/tests/test_md_files/test_card_guid.md
personal_mnemonic_medium-0.6.0.dist-info/METADATA
personal_mnemonic_medium-0.6.0.dist-info/WHEEL
personal_mnemonic_medium-0.6.0.dist-info/top_level.txt
personal_mnemonic_medium-0.6.0.dist-info/RECORD
