Metadata-Version: 2.1
Name: personal-mnemonic-medium
Version: 0.6.0
Summary: Personal Mnemonic Medium
Author-email: Martin Bernstorff <martinbernstorff@gmail.com>
Project-URL: homepage, https://github.com/MartinBernstorff/personal-mnemonic-medium
Project-URL: repository, https://github.com/MartinBernstorff/personal-mnemonic-medium
Project-URL: documentation, https://MartinBernstorff.github.io/personal-mnemonic-medium/
Classifier: Programming Language :: Python :: 3.11
Requires-Python: >=3.11
Requires-Dist: functionalpy ==0.6.0
Requires-Dist: misaka ==2.1.1
Requires-Dist: genanki ==0.13.0
Requires-Dist: typer ==0.9.0
Requires-Dist: wasabi ==1.1.2
Requires-Dist: tqdm ==4.66.1
Requires-Dist: sentry-sdk ==1.32.0
Requires-Dist: cffi ==1.16.0
Provides-Extra: dev
Requires-Dist: cruft ==2.15.0 ; extra == 'dev'
Requires-Dist: pyright ==1.1.328 ; extra == 'dev'
Requires-Dist: pre-commit ==2.20.0 ; extra == 'dev'
Requires-Dist: ruff ==0.1.3 ; extra == 'dev'
Requires-Dist: black ==22.8.0 ; extra == 'dev'
Provides-Extra: tests
Requires-Dist: pytest ==7.1.3 ; extra == 'tests'
Requires-Dist: pytest-cov ==3.0.0 ; extra == 'tests'
Requires-Dist: pytest-xdist ==3.3.1 ; extra == 'tests'
Requires-Dist: pytest-sugar ==0.9.7 ; extra == 'tests'
